ukr_bible/__init__.py
ukr_bible/aliases.py
ukr_bible/core.py
ukr_bible/models.py
ukr_bible/ukr_bible_data.json
ukr_bible-0.1.0.dist-info/METADATA
ukr_bible-0.1.0.dist-info/WHEEL
ukr_bible-0.1.0.dist-info/top_level.txt
ukr_bible-0.1.0.dist-info/RECORD
