Metadata-Version: 2.4
Name: ukr-bible
Version: 0.1.0
Summary: A Python library for the Ukrainian Bible (Ohienko translation).
Author-email: Ivan Tsiak <ivanzjak2007@gmail.com>
Project-URL: Homepage, https://github.com/твоє_ім'я/ukr-bible
Keywords: bible,ukrainian,ohienko,біблія,релігія
Classifier: Programming Language :: Python :: 3
Classifier: License :: OSI Approved :: MIT License
Classifier: Operating System :: OS Independent
Classifier: Natural Language :: Ukrainian
Requires-Python: >=3.7
